setup.cfg
setup.py
httputil/__init__.py
httputil/httputil.py
httputil.egg-info/PKG-INFO
httputil.egg-info/SOURCES.txt
httputil.egg-info/dependency_links.txt
httputil.egg-info/requires.txt
httputil.egg-info/top_level.txt
httputil/request_engines/__init__.py
httputil/request_engines/async.py
httputil/request_engines/base.py
httputil/request_engines/errors.py
httputil/request_engines/sync.py