Metadata-Version: 1.1
Name: httputil
Version: 0.5.1
Summary: Various utilities to deal with HTTP stuff.
Home-page: https://github.com/vovanec/httputil
Author: Vovan Kuznetsov
Author-email: vovanec@gmail.com
License: MIT
Download-URL: https://github.com/vovanec/httputil/tarball/0.5.1
Keywords: http,dechunk,decompress,client,request
Platform: UNKNOWN
Classifier: License :: OSI Approved :: MIT License
Classifier: Development Status :: 4 - Beta
Classifier: Intended Audience :: Developers
Classifier: Programming Language :: Python :: 3.4
